ChangeLog.rst
LICENSE
MANIFEST.in
README.rst
setup.py
mrepserver/__init__.py
mrepserver/server.py
mrepserver.egg-info/PKG-INFO
mrepserver.egg-info/SOURCES.txt
mrepserver.egg-info/dependency_links.txt
mrepserver.egg-info/requires.txt
mrepserver.egg-info/top_level.txt
mrepserver/template/find.html
scripts/mrepserver