Metadata-Version: 1.1
Name: mrepserver
Version: 0.1.0
Summary: MREP server: morpheme regular expression printer
Home-page: https://github.com/unnonouno/mrepserver
Author: Yuya Unno
Author-email: unnonouno@gmail.com
License: MIT
Platform: UNKNOWN
Classifier: Operating System :: OS Independent
Classifier: Environment :: Web Environment
Classifier: Programming Language :: Python
Classifier: License :: OSI Approved :: MIT License
Classifier: Development Status :: 2 - Pre-Alpha
Classifier: Intended Audience :: Information Technology
Classifier: Intended Audience :: Science/Research
Classifier: Topic :: Utilities
